pyciv7/__init__.py
pyciv7/databases/__init__.py
pyciv7/databases/colors/__init__.py
pyciv7/databases/frontend/__init__.py
pyciv7/databases/gameplay/__init__.py
pyciv7/databases/hall_of_fame/__init__.py
pyciv7/databases/images/__init__.py
pyciv7/databases/local_storage/__init__.py
pyciv7/databases/localization/__init__.py
pyciv7/databases/mods/__init__.py
pyciv7/errors.py
pyciv7/modinfo.py
pyciv7/modinfo_extensions.py
pyciv7/py.typed
pyciv7/resources/transcrypt_hook.js
pyciv7/runner.py
pyciv7/settings.py
pyciv7/utils.py
pyciv7-1.1.0.dist-info/WHEEL
pyciv7-1.1.0.dist-info/METADATA
pyciv7-1.1.0.dist-info/RECORD
