Metadata-Version: 2.3
Name: pyciv7
Version: 1.1.0
Summary: Python bindings for the Sid Meier's Civilization VII Software Development Kit (SDK)
Keywords: civilization,civ7,sdk,python bindings
Author: Dylan Manuel
License: MIT License
Classifier: Development Status :: 3 - Alpha
Classifier: Intended Audience :: Developers
Classifier: License :: OSI Approved :: MIT License
Classifier: Programming Language :: Python :: 3.9
Classifier: Programming Language :: Python :: 3.10
Classifier: Programming Language :: Python :: 3.11
Classifier: Programming Language :: Python :: 3.12
Classifier: Operating System :: OS Independent
Classifier: Topic :: Software Development :: Libraries
Classifier: Topic :: Games/Entertainment
Requires-Dist: pydantic-settings>=2.0.3
Requires-Dist: pydantic-xml>=2.17.3
Requires-Dist: rich>=13.8.1
Requires-Dist: sqlmodel>=0.0.24
Requires-Dist: transcrypt>=3.9.4
Requires-Python: >3.8, <3.14
Project-URL: Bug Tracker, https://github.com/dmanuel64/pyciv7/issues
Project-URL: Homepage, https://github.com/dmanuel64/pyciv7
Project-URL: Repository, https://github.com/dmanuel64/pyciv7
